probart/__init__.py
probart/canvas.py
probart-0.1.0.dist-info/LICENSE
probart-0.1.0.dist-info/METADATA
probart-0.1.0.dist-info/WHEEL
probart-0.1.0.dist-info/top_level.txt
probart-0.1.0.dist-info/RECORD
