Metadata-Version: 2.1
Name: probart
Version: 0.1.0
Summary: Tiny library for probabilistic line drawing
Home-page: https://github.com/a5kin/probart
Author: Andrey Zamaraev
Author-email: a5kin@github.com
License: MIT
Keywords: probabilistic drawing tools utils utility
Platform: UNKNOWN
Classifier: Development Status :: 3 - Alpha
Classifier: Environment :: Console
Classifier: Topic :: Artistic Software
Classifier: Topic :: Utilities
Classifier: License :: OSI Approved :: MIT License
Classifier: Programming Language :: Python :: 3
Requires-Dist: numpy
Requires-Dist: pycairo
Provides-Extra: dev
Requires-Dist: check-manifest ; extra == 'dev'
Provides-Extra: test
Requires-Dist: coverage ; extra == 'test'
